{
    "status":true,
    "studenteId":"630610727",
    "transcript":[
       {
          "year":2563,
          "yearDetails":[
             {
                "semester":1,
                "details":[
                   {
                      "code":"001101",
                      "credit":3,
                      "grade":"B"
                   },
                   {
                      "code":"140104",
                      "credit":3,
                      "grade":"B+"
                   },
                   {
                      "code":"206161",
                      "credit":3,
                      "grade":"F"
                   },
                   {
                      "code":"207105",
                      "credit":3,
                      "grade":"C+"
                   },
                   {
                      "code":"207115",
                      "credit":1,
                      "grade":"A"
                   },
                   {
                      "code":"259104",
                      "credit":3,
                      "grade":"B"
                   },
                   {
                      "code":"259106",
                      "credit":1,
                      "grade":"B+"
                   },
                   {
                      "code":"259191",
                      "credit":1,
                      "grade":"S"
                   },
                   {
                      "code":"261103",
                      "credit":3,
                      "grade":"A"
                   }
                ]
             },
             {
                "semester":2,
                "details":[
                   {
                      "code":"001102",
                      "credit":3,
                      "grade":"B+"
                   },
                   {
                      "code":"109114",
                      "credit":3,
                      "grade":"A"
                   },
                   {
                      "code":"206161",
                      "credit":3,
                      "grade":"F"
                   },
                   {
                      "code":"207106",
                      "credit":3,
                      "grade":"C+"
                   },
                   {
                      "code":"207116",
                      "credit":1,
                      "grade":"A"
                   },
                   {
                      "code":"252281",
                      "credit":3,
                      "grade":"B"
                   },
                   {
                      "code":"261102",
                      "credit":3,
                      "grade":"B+"
                   }
                ]
             }
          ]
       },
       {
          "year":2564,
          "yearDetails":[
             {
                "semester":1,
                "details":[
                   {
                      "code":"001201",
                      "credit":3,
                      "grade":"B+"
                   },
                   {
                    "code":"206161",
                    "credit":3,
                    "grade":"D"
                 },
                   {
                      "code":"211100",
                      "credit":3,
                      "grade":"A"
                   },
                   {
                      "code":"261207",
                      "credit":2,
                      "grade":"B+"
                   },
                   {
                      "code":"261210",
                      "credit":3,
                      "grade":"B+"
                   },
                   {
                      "code":"261212",
                      "credit":1,
                      "grade":"A"
                   },
                   {
                      "code":"261216",
                      "credit":3,
                      "grade":"B+"
                   },
                   {
                      "code":"261217",
                      "credit":3,
                      "grade":"B+"
                   }
                ]
             },
             {
                "semester":2,
                "details":[
                   {
                      "code":"001225",
                      "credit":3,
                      "grade":"C+"
                   },
                   {
                    "code":"206162",
                    "credit":3,
                    "grade":"W"
                 },
                   {
                      "code":"261200",
                      "credit":3,
                      "grade":"B+"
                   },
                   {
                      "code":"261214",
                      "credit":3,
                      "grade":"B+"
                   },
                   {
                      "code":"261215",
                      "credit":1,
                      "grade":"A"
                   },
                   {
                      "code":"261218",
                      "credit":3,
                      "grade":"B+"
                   },
                   {
                      "code":"261332",
                      "credit":3,
                      "grade":"B+"
                   }
                ]
             },
             {
                "semester":3,
                "details":[
                   {
                    "code":"206162",
                    "credit":3,
                    "grade":"C"
                 }
                ]
             }

          ]
       },
       {
          "year":2565,
          "yearDetails":[
             {
                "semester":1,
                "details":[
                   {
                      "code":"201114",
                      "credit":3,
                      "grade":"B+"
                   },
                   {
                    "code":"206261",
                    "credit":3,
                    "grade":"W"
                 },
                   {
                      "code":"261304",
                      "credit":3,
                      "grade":"B+"
                   },
                   {
                      "code":"261335",
                      "credit":3,
                      "grade":"B+"
                   },
                   {
                      "code":"261336",
                      "credit":1,
                      "grade":"B+"
                   },
                   {
                      "code":"261342",
                      "credit":3,
                      "grade":"A"
                   },
                   {
                      "code":"261343",
                      "credit":1,
                      "grade":"A"
                   },
                   {
                      "code":"261494",
                      "credit":3,
                      "grade":"A"
                   }
                ]
             },
             {
                "semester":2,
                "details":[
                    {
                        "code":"206261",
                        "credit":3,
                        "grade":"W"
                     },
                   {
                      "code":"259194",
                      "credit":3,
                      "grade":"S"
                   },
                   {
                      "code":"261111",
                      "credit":3,
                      "grade":"A"
                   },
                   {
                      "code":"261305",
                      "credit":3,
                      "grade":"A"
                   },
                   {
                      "code":"261361",
                      "credit":3,
                      "grade":"A"
                   },
                   {
                      "code":"261441",
                      "credit":3,
                      "grade":"A"
                   }
                ]
             }
          ]
       },
       {
          "year":2566,
          "yearDetails":[
             {
                "semester":1,
                "details":[
                    {
                        "code":"206261",
                        "credit":3,
                        "grade":"C"
                     },
                   {
                      "code":"261449",
                      "credit":3,
                      "grade":"A"
                   },
                   {
                      "code":"261458",
                      "credit":3,
                      "grade":"W"
                   },
                   {
                      "code":"261470",
                      "credit":3,
                      "grade":"A"
                   },
                   {
                      "code":"261491",
                      "credit":1,
                      "grade":"S"
                   },
                   {
                      "code":"357101",
                      "credit":3,
                      "grade":"W"
                   }
                ]
             },
             {
                "semester":2,
                "details":[
                    {
                        "code":"206261",
                        "credit":3,
                        "grade":"W"
                     },
                     {
                        "code":"261208",
                        "credit":3,
                        "grade":"W"
                     },
                     {
                        "code":"259192",
                        "credit":3,
                        "grade":"S"
                     },
                   {
                      "code":"261405",
                      "credit":3,
                      "grade":"A"
                   },
                   {
                      "code":"261459",
                      "credit":3,
                      "grade":"F"
                   },
                   {
                      "code":"261492",
                      "credit":3,
                      "grade":"A"
                   },
                   {
                      "code":"361100",
                      "credit":3,
                      "grade":"A"
                   }
                ]
             },
             {
                "semester":3,
                "details":[
                    {
                        "code":"357101",
                        "credit":3,
                        "grade":"A"
                     },
                     {
                        "code":"357792",
                        "credit":3,
                        "grade":"A"
                     }
                ]
             }
          ]
       },
       {
        "year":2567,
        "yearDetails":[
           {
              "semester":1,
              "details":[
                 {
                    "code":"261421",
                    "credit":3,
                    "grade":"A"
                 },
                 {
                    "code":"261437",
                    "credit":3,
                    "grade":"A"
                 }
              ]
           },
           {
            "semester":2,
            "details":[
                {
                    "code":"201114",
                    "credit":3,
                    "grade":"A"
                 },{
                  "code":"261208",
                  "credit":3,
                  "grade":"A"
               },
               {
                  "code":"261306",
                  "credit":3,
                  "grade":"A"
               }
            ]
         }
        ]
     }
    ]
  }